contract/__init__.py
contract_decorator-2020.10.27.dist-info/LICENSE
contract_decorator-2020.10.27.dist-info/METADATA
contract_decorator-2020.10.27.dist-info/WHEEL
contract_decorator-2020.10.27.dist-info/top_level.txt
contract_decorator-2020.10.27.dist-info/RECORD
