Metadata-Version: 2.1
Name: contract-decorator
Version: 2020.10.27
Summary: A simple decorator used for parameter checking
Home-page: https://github.com/ccorsi/contract
Author: Claudio Corsi
Author-email: clcorsi@yahoo.com
License: UNKNOWN
Platform: UNKNOWN
Classifier: Programming Language :: Python :: 3
Classifier: License :: OSI Approved :: Apache Software License
Classifier: Operating System :: OS Independent
Requires-Python: >=3.5
